bokodapviewer/App.py
bokodapviewer/Config.xml
bokodapviewer/__init__.py
bokodapviewer-0.6.0.dist-info/licenses/LICENSE.md
bokodapviewer-0.6.0.dist-info/METADATA
bokodapviewer-0.6.0.dist-info/WHEEL
bokodapviewer-0.6.0.dist-info/top_level.txt
bokodapviewer-0.6.0.dist-info/RECORD
