Metadata-Version: 2.4
Name: bokodapviewer
Version: 0.6.0
Summary: A simple OpenDAP data viewer based on the Bokeh visualisation library
Home-page: https://github.com/marcuskd/bokodapviewer
Author: Marcus Donnelly
Author-email: marcus.k.donnelly@gmail.com
License: BSD 3-Clause
Keywords: OpenDAP,Bokeh,Environment,Science
Classifier: Development Status :: 4 - Beta
Classifier: Intended Audience :: Science/Research
Classifier: License :: OSI Approved :: MIT License
Classifier: Programming Language :: Python :: 3
Classifier: Topic :: Scientific/Engineering
License-File: LICENSE.md
Requires-Dist: numpy>=1.23
Requires-Dist: bokeh>=3
Requires-Dist: bokcolmaps>=4.3
Requires-Dist: sodapclient>=0.3
Requires-Dist: interpg>=1.1
Dynamic: author
Dynamic: author-email
Dynamic: classifier
Dynamic: home-page
Dynamic: keywords
Dynamic: license
Dynamic: license-file
Dynamic: requires-dist
Dynamic: summary
